vnpy_sgit/__init__.py
vnpy_sgit/api/__init__.py
vnpy_sgit/api/libcrypto.so
vnpy_sgit/api/libcrypto.so.10
vnpy_sgit/api/libsgitquotapi.so
vnpy_sgit/api/libsgittradeapi.so
vnpy_sgit/api/libssl.so
vnpy_sgit/api/libssl.so.10
vnpy_sgit/api/rsa.pk
vnpy_sgit/api/sgit_constant.py
vnpy_sgit/api/include/pybind11/attr.h
vnpy_sgit/api/include/pybind11/buffer_info.h
vnpy_sgit/api/include/pybind11/cast.h
vnpy_sgit/api/include/pybind11/chrono.h
vnpy_sgit/api/include/pybind11/common.h
vnpy_sgit/api/include/pybind11/complex.h
vnpy_sgit/api/include/pybind11/eigen.h
vnpy_sgit/api/include/pybind11/embed.h
vnpy_sgit/api/include/pybind11/eval.h
vnpy_sgit/api/include/pybind11/functional.h
vnpy_sgit/api/include/pybind11/iostream.h
vnpy_sgit/api/include/pybind11/numpy.h
vnpy_sgit/api/include/pybind11/operators.h
vnpy_sgit/api/include/pybind11/options.h
vnpy_sgit/api/include/pybind11/pybind11.h
vnpy_sgit/api/include/pybind11/pytypes.h
vnpy_sgit/api/include/pybind11/stl.h
vnpy_sgit/api/include/pybind11/stl_bind.h
vnpy_sgit/api/include/pybind11/detail/class.h
vnpy_sgit/api/include/pybind11/detail/common.h
vnpy_sgit/api/include/pybind11/detail/descr.h
vnpy_sgit/api/include/pybind11/detail/init.h
vnpy_sgit/api/include/pybind11/detail/internals.h
vnpy_sgit/api/include/pybind11/detail/typeid.h
vnpy_sgit/api/include/sgit/SgitFtdcMdApi.h
vnpy_sgit/api/include/sgit/SgitFtdcTraderApi.h
vnpy_sgit/api/include/sgit/SgitFtdcUserApiDataType.h
vnpy_sgit/api/include/sgit/SgitFtdcUserApiStruct.h
vnpy_sgit/api/vnsgit/vnsgit.h
vnpy_sgit/api/vnsgit/vnsgitmd/dllmain.cpp
vnpy_sgit/api/vnsgit/vnsgitmd/stdafx.cpp
vnpy_sgit/api/vnsgit/vnsgitmd/stdafx.h
vnpy_sgit/api/vnsgit/vnsgitmd/targetver.h
vnpy_sgit/api/vnsgit/vnsgitmd/vnsgitmd.cpp
vnpy_sgit/api/vnsgit/vnsgitmd/vnsgitmd.h
vnpy_sgit/api/vnsgit/vnsgittd/dllmain.cpp
vnpy_sgit/api/vnsgit/vnsgittd/stdafx.cpp
vnpy_sgit/api/vnsgit/vnsgittd/stdafx.h
vnpy_sgit/api/vnsgit/vnsgittd/targetver.h
vnpy_sgit/api/vnsgit/vnsgittd/vnsgittd.cpp
vnpy_sgit-4.8.4.dist-info/LICENSE
vnpy_sgit-4.8.4.dist-info/METADATA
vnpy_sgit-4.8.4.dist-info/WHEEL
vnpy_sgit-4.8.4.dist-info/top_level.txt
vnpy_sgit-4.8.4.dist-info/RECORD
